Workbook

Sheet 模型定价假设
A1: Qwen3.7-Plus 定价与成本假设
A3: 模型名称 | B3: Qwen3.7-Plus | C3: 风格分析 + 文章生成 同一模型
A4: 输入单价（≤256k） | B4: 1.6 | C4: ¥/M tokens，截图限时 8 折价
A5: 输出单价（≤256k） | B5: 6.4 | C5: ¥/M tokens，截图限时 8 折价
A6: 每汉字 ≈ tokens | B6: 1.5 | C6: 中文经验值，用于估算输出 token
A7: 文章基础输入 tokens | B7: 1500 | C7: 风格档案(约1000) + 写作要求(约500)
A8: 平均单积分成本(¥) | B8: 0.0043 | C8: 按 2000字中篇测算：输入1500+输出3000 tokens = ¥0.0216 / 5积分
A9: 积分定位 | B9: 用量配额单位 | C9: 1 积分为用户侧配额单位，与人民币非 1:1，仅用于限制用量；真实成本按 token 另计

Sheet 操作积分设计
A1: 每个操作的花费积分设计
A3: 一、文章生成（按长度分档，长文享折扣）
A4: 长度档（字） | B4: 消耗积分 | C4: 每千字平均积分 | D4: 说明
A5: ≤1000 | B5: 3 | C5: =B5/(VALUE(SUBSTITUTE(A5,"≤",""))/1000) | D5: 基础档，单价最高
A6: ≤2000 | B6: 5 | C6: =B6/(VALUE(SUBSTITUTE(A6,"≤",""))/1000) | D6: 比 1000 字档单位更便宜（折扣）
A7: ≤3000 | B7: 8 | C7: =B7/(VALUE(SUBSTITUTE(A7,"≤",""))/1000) | D7: 锚点：更长内容单位价更低
A8: ≤4000 | B8: 11 | C8: =B8/(VALUE(SUBSTITUTE(A8,"≤",""))/1000) | D8: 之后每千字约 +3 分
A9: ≤5000 | B9: 14 | C9: =B9/(VALUE(SUBSTITUTE(A9,"≤",""))/1000)
A10: ≤8000 | B10: 22 | C10: =B10/(VALUE(SUBSTITUTE(A10,"≤",""))/1000) | D10: 长文创作场景
A11: ≤10000 | B11: 29 | C11: =B11/(VALUE(SUBSTITUTE(A11,"≤",""))/1000) | D11: 上限，超出需联系商务
A13: 二、其他操作（固定积分）
A14: 操作 | B14: 消耗积分 | C14: 每千字平均积分 | D14: 说明
A15: 风格分析 | B15: 2 | C15: — | D15: 上传作品诊断六维风格，一次性动作
A16: 段落重写 | B16: 1 | C16: — | D16: 每次重写消耗，与长度无关
A17: 风格档案编辑 | B17: 0 | C17: — | D17: 免费，不计入额度
A18: 文章保存/下载 | B18: 0 | C18: — | D18: 免费，不计入额度（仅付费档开放功能）

Sheet 用户等级套餐
A1: 用户等级与积分套餐设计
A3: 等级 | B3: 月费(¥) | C3: 月积分 | D3: 约可生成中篇(2000字) | E3: 风格上限 | F3: 作品上限 | G3: 下载docx | H3: 段落重写 | I3: 满额成本(¥) | J3: 毛利率
A4: 免费版 | B4: 0 | C4: 10 | D4: =C4/5 | E4: 2 | F4: 3 | G4: 否 | H4: 否 | I4: =C4*模型定价假设!$B$8 | J4: N/A
A5: 基础版 | B5: 19 | C5: 60 | D5: =C5/5 | E5: 10 | F5: 20 | G5: 是 | H5: 是 | I5: =C5*模型定价假设!$B$8 | J5: =(B5-I5)/B5
A6: 专业版 | B6: 49 | C6: 200 | D6: =C6/5 | E6: 30 | F6: 100 | G6: 是 | H6: 是 | I6: =C6*模型定价假设!$B$8 | J6: =(B6-I6)/B6
A7: 团队版 | B7: 199 | C7: 1000 | D7: 不限 | E7: 不限 | F7: 不限 | G7: 是 | H7: 是 | I7: =C7*模型定价假设!$B$8 | J7: =(B7-I7)/B7
A9: 注：免费版仅可生成 ≤2000字 内容；付费档开放下载/重写；团队版含成员管理与共享风格。满额成本按平均单积分成本(¥0.0043)测算。

Sheet 盈亏平衡测算
A1: 以「专业版 ¥49/月，200 积分」为例：不同使用率下的真实利润
A3: 使用率 | B3: 实际消耗积分 | C3: 实际成本(¥) | D3: 月收入(¥) | E3: 毛利(¥) | F3: 毛利率
A4: 20% | B4: =200*0.2 | C4: =B4*模型定价假设!$B$8 | D4: 49 | E4: =D4-C4 | F4: =E4/D4
A5: 50% | B5: =200*0.5 | C5: =B5*模型定价假设!$B$8 | D5: 49 | E5: =D5-C5 | F5: =E5/D5
A6: 100% | B6: =200*1.0 | C6: =B6*模型定价假设!$B$8 | D6: 49 | E6: =D6-C6 | F6: =E6/D6

Sheet 设计说明
A1: 用量与额度 · 设计说明
A3: 一、积分定位
A4: · 积分为「用户侧用量配额单位」，不直接等于人民币，目的是与具体模型解耦，便于换模型/做促销。
A5: · 真实成本按每次调用的 input/output token 实时计算（见模型定价假设），用于我们内部核算，不展示给用户。
A6: · 用户看到的只有「本次消耗 X 积分」和「本月剩余 Y 积分」。
A8: 二、文章计费折扣逻辑
A9: · 按输出字数分档：1000字=3分、2000字=5分、3000字=8分（用户给定锚点）。
A10: · 不是严格线性：前 1000 字单价最高(3.0 分/千字)，2000 字档最低(2.5 分/千字)，更长趋于 ~2.7 分/千字，相当于「写得越长越划算」，引导深度创作。
A11: · 超过 10000 字需联系商务或单独计费。
A13: 三、其他操作
A14: · 风格分析 2 分（一次性诊断）；段落重写 1 分/次；风格编辑、保存、下载本身免费，仅按等级开放功能权限。
A16: 四、用户等级与权限
... A30: · 每月 quota_resets_at 到期自动重置 used_quota=0。
